{
    "id": 36,
    "country": "IS",
    "artist": "María Ólafsdóttir",
    "song": "Unbroken",
    "lyrics": [
        {
            "languages": [
                "English version"
            ],
            "title": "Unbroken",
            "content": "One step at a time\nOut of the darkness\nOne foot in front of the other\n\nOne step at a time\nInto the distance\nA new path I need to uncover\n\nI'm letting go\nGo\n\nOne step at a time\nGet out of the darkness\nAnd into the light forever\nOne step at a time\nI pick up the pieces\nTry putting them back together\nTill I'm unbroken\nUnbroken\nOne step at a time\nGet out of the darkness\nAnd into the light forever\n\nOne step at a time\nAnd I got a feeling\nIt's either now or never\n\nI'm letting go\nGo\n\nOne step at a time\nGet out of the darkness\nAnd into the light forever\nOne step at a time\nI pick up the pieces\nTry putting them back together\nTill I'm unbroken\nUnbroken\n\nOne step at a time\nGet out of the darkness\nAnd into the light forever\n\nI'm letting gon\nGo\n\nOne step at a time\nGet out of the darkness\nAnd into the light forever\nOne step at a time\nI pick up the pieces\nTry putting them back together\nTill I'm unbroken\nUnbroken\n\nOne step at a time\nGet out of the darkness\nAnd into the light forever\n\nI'm letting go\nGo\n\nOne step at a time\nGet out of the darkness\nAnd into the light forever\nOne step at a time\nI pick up the pieces\nTry putting them back together\n'Til I'm unbroken\nUnbroken\n\nOne step at a time\nGet out of the dаrknesѕ\nAnd into the light forever"
        },
        {
            "languages": [
                "Icelandic version"
            ],
            "title": "Lítil Skref",
            "content": "Tek lítil skref og reyni að gleyma\nGleyma því sem þú sagðir\nLítil skref og stari út í myrkrið\nGeng hægt í áttina frá þér\n\nEftir langri slóð, langri slóð\n\nTek lítil skref en held alltaf áfram\nHeld áfram í áttina frá þér\nLítil skref og mun ekki stoppa\nHeld áfram í áttina frá þér\nOg ég verð heil á ný, heil á ný\nTek lítil skref en held alltaf áfram\nHeld áfram í áttina frá þér\n\nTek lítil skref en þegar ég horfi til baka\nSé ég þig varla í fjarska\n\nSé bara langa slóð, langa slóð\n\nTek lítil skref en held alltaf áfram\nHeld áfram í áttina frá þér\nLítil skref og mun ekki stoppa\nHeld áfram í áttina frá þér\nOg ég verð heil á ný, heil á ný\nTek lítil skref en held alltaf áfram\nHeld áfram í áttina frá þér\n\nEftir langri slóð, langri slóð\n\nTek lítil skref en held alltaf áfram\nHeld áfram í áttina frá þér\nLítil skref og mun ekki stoppa\nHeld áfram í áttina frá þér\nOg ég verð heil á ný, heil á ný\nTek lítil ѕkref en held alltaf áfram\nHeld áfram í áttinа frá þér"
        }
    ],
    "videoUrls": [
        "https://www.youtube-nocookie.com/embed/0Jl-Hr137uM",
        "https://www.youtube.com/embed/sov_pE1cdFY",
        "https://www.youtube.com/embed/iJ-buMRXXKM"
    ],
    "dancers": null,
    "backings": [
        "Alma Rut Kristinsdóttir",
        "Ásgeir Orri Ásgeirsson",
        "Friðrik Dór",
        "Hera Björk",
        "Íris Hólm Jónsdóttir"
    ],
    "composers": [
        "Ásgeir Orri Ásgeirsson",
        "Pálmi Ragnar Ásgeirsson",
        "Sæþór Kristjánsson"
    ],
    "lyricists": [
        "Ásgeir Orri Ásgeirsson",
        "María Ólafsdóttir",
        "Pálmi Ragnar Ásgeirsson",
        "Sæþór Kristjánsson"
    ],
    "writers": null,
    "conductor": null,
    "stageDirector": null,
    "tone": "C# major",
    "bpm": 97,
    "broadcaster": "RÚV",
    "spokesperson": "Sigríður Halldórsdóttir",
    "commentators": [
        "Felix Bergsson"
    ]
}