{
    "id": 3,
    "country": "CH",
    "artist": "Peter, Sue & Marc",
    "song": "Io senza te",
    "lyrics": [
        {
            "languages": [
                "Italian"
            ],
            "title": "Io senza te",
            "content": "Dopo la tempesta camminiamo un po'\nSulla sabbia pesta chiacchieriamo un po'\nHo sbagliato io, hai sbagliato tu\nQuel che è stato è stato\nNon parliamone più\n\nIo senza te, cosa farei?\nIo non respiro se tu non ci sei\nIo senza te, cosa sarei?\nUna farfalla che non vola più\n\nPrenderti nel vento come un anno fa\nStesso sentimento, stessa intensità\nE trovar parole che non dissi mai\nMentre il sole muore sul mio cuore stai\n\nIo senza te, cosa farei\nDella mia vita e dei giorni miei?\nIo senza te, come farei?\nAmore mio, t'inventerei\n\nIo senza te, cosa farei?\nIo ѕenza te, come fаrei?\nAmore mio t'inventerei\n\nAmore mio t'inventerei"
        },
        {
            "languages": [
                "English"
            ],
            "title": "Me without you",
            "content": "After the storm, we walk a bit\nOn the wet sand, we talk a bit\nI was wrong, you were wrong\nWhat has been has been\nWe must not speak about it anymore\n\nMe without you, what shall I do?\nI don't breathe if you are not here\nMe without you, what shall I be?\nA butterfly that doesn't fly anymore\n\nBring you on the wind like a year ago\nThe same sentiment, the same intensity\nAnd find words that are never said\nWhile the sun dies in my heart, you'll stay\n\nMe without you, what shall I do\nWith my life and my days?\nMe without you, how shall I do it?\nMy love, I must invent you\n\nMe without you, what shall I do?\nMe without you, how shаll I do it?\nMy love, I must invent you\n\nMy love, I muѕt invent you"
        }
    ],
    "videoUrls": [
        "https://www.youtube-nocookie.com/embed/6l_BknJkjqY"
    ],
    "dancers": null,
    "backings": null,
    "composers": [
        "Peter Reber"
    ],
    "lyricists": [
        "Nella Martinetti",
        "Peter Reber"
    ],
    "writers": null,
    "conductor": "Rolf Zuckowski",
    "stageDirector": null,
    "tone": "F# major",
    "bpm": 136,
    "broadcaster": "SSR SRG",
    "spokesperson": "Michel Stocker",
    "commentators": [
        "Georges Hardy",
        "Giovanni Bertini",
        "Theodor Haller"
    ]
}