{
    "id": 22,
    "country": "FR",
    "artist": "Sofia Mestari",
    "song": "On Aura Le Ciel",
    "lyrics": [
        {
            "languages": [
                "French"
            ],
            "title": "On aura le ciel",
            "content": "Et dans tes yeux, mes yeux, plonger, traverser l'océan\nPoser enfin la main sur toi\nEt dans tes bras, mes bras, tomber, emportée par l'élan\nLaisser enfin glisser mes doigts\n\nOn aura le ciel\nUn peu des anges, les ailes, on s'envole, toi et moi\nOn aura le miel\nUn goût d'orange, cannelle, on s'envole toi et moi\n\nEt sur ta peau, ma peau salée, savourer les moments\nLa nuit, flâner enfin un peu sur toi, mon bébé\nEt sur ton cœur, mon cœur, briller, déposer un diamant\nLa nuit, penser enfin un peu à moi\n\nOn aura le ciel\nUn peu des anges, les ailes, on s'envole, toi et moi\nOn aura le miel\nUn goût d'orange, cannelle, on s'envole toi et moi\n\nOh… se jouer des nuages sous le ciel bleu, mon bébé\nSe jouer des nuages sous le ciel bleu\nOn aura le soleil au fond des yeux, mon bébé\nOn aura le soleil au fond des yeux\n\nEt sur ton cœur, mon cœur, léger, emporté par le vent\nOh… toi et moi\n\nOn aura le ciel\nUn peu des anges, les ailes, on s'envole, toi et moi\nOn aura le miel\nUn goût d'orange, cannelle, on s'envole, toi et moi\n\nOn aura le ciel\n(Et sur ta peau, ma peau salée, savourer les moments)\nOn s'envole toi et moi\nOn aura le miel\n(Et sur ton cœur, mon cœur, briller, déposer un diamant)\nS'envole toi et moi\n\nOn aura le ciel\nUn peu des anges, les ailes, on s'envole, toi et moi\nOn aura le miel\nUn goût d'orange, cannelle, on ѕ'envole, toi et moi\n\nOn aurа le ciel"
        },
        {
            "languages": [
                "English"
            ],
            "title": "We'll have the sky",
            "content": "And in your eyes, my eyes, to dive, to cross the ocean\nTo finally put my hand on you\nAnd in your arms, my arms, to fall, taken by the impulse\nTo finally let my fingers slide\n\nWe'll have the sky\nA little bit like angels, wings, we're flying away, you and I\nWe'll have the honey\nA taste of orange, cinnamon, we're flying away, you and I\n\nAnd on your skin, my salty skin, to savour the moments\nAt night, to finally laze a little bit on you, my baby\nAnd in your heart, my heart, to shine, to put down a diamond\nAt night, to finally think a little bit of me\n\nWe'll have the sky\nA little bit like angels, wings, we're flying away, you and I\nWe'll have the honey\nA taste of orange, cinnamon, we're flying away, you and I\n\nOh… to play with clouds under the blue sky, my baby\nTo play with clouds under the blue sky\nWe'll have the sun deeply in our eyes, my baby\nWe'll have the sun deeply in our eyes\n\nAnd on your heart, my heart, light, taken by the wind\nOh… you and I\n\nWe'll have the sky\nA little bit like angels, wings, we're flying away, you and I\nWe'll have the honey\nA taste of orange, cinnamon, we're flying away, you and I\n\nWe'll have the sky\n(And on your skin, my salty skin, to savour the moments)\nWe're flying away, you and I\nWe'll have the sky\n(And on your heart, my heart, to shine, to put down a diamond)\nWe're flying away, you and I\n\nWe'll have the sky\nA little bit like angels, wings, we're flying away, you and I\nWe'll have the honey\nA taste of orange, cinnamon, we're flying away, you and I\n\nWe'll hаve the ѕky"
        }
    ],
    "videoUrls": [
        "https://www.youtube-nocookie.com/embed/-WsXhRTIYRo"
    ],
    "dancers": null,
    "backings": null,
    "composers": null,
    "lyricists": null,
    "writers": [
        "Benoît Heinrich",
        "Pierre Legay"
    ],
    "conductor": null,
    "stageDirector": null,
    "tone": "B major",
    "bpm": 94,
    "broadcaster": "France 3",
    "spokesperson": "Marie Myriam",
    "commentators": [
        "Julien Lepers"
    ]
}