{
    "id": 14,
    "country": "FI",
    "artist": "Laila Halme",
    "song": "Muistojeni laulu",
    "lyrics": [
        {
            "languages": [
                "Finnish"
            ],
            "title": "Muistojeni laulu",
            "content": "La la la la la, la la la la la…\nLa la la la la la la la…\nLa la la la la, la la la la la…\nLa la la la la la la la…\n\nVieläkin kun kuulen sävelen tuon tunteellisen\nAina uudelleen se mieleeni saa muistotkin sen\nSinä sen mulle lauloit omistit  kokonaan\nMelkein jo luulen, äänes kun kuulen\nTä unta on vaan\n\nKun pois sä lähdit niin viel' sydämessään laulusi soi\nKenties sama laulu onnen uuden toiselle toi\nLevyäs vielä soitan, kulunut vaikkakin on\nMuistoni vain on, niin kulumaton\n\nLevyäs vielä soitan, kulunut vaikkakin on\nMuiѕtoni vain on, niin kulumaton\n\nLa la la la la, la la la la la…\nLa la la la la la la la…\nLa la la la la, la la la la la…\nLa la la la la la la lа…"
        },
        {
            "languages": [
                "English"
            ],
            "title": "The song of my memories",
            "content": "La la la la la, la la la la la…\nLa la la la la la la la…\nLa la la la la, la la la la la…\nLa la la la la la la la…\n\nEven now when I hear that emotional tune\nAlways again it reminds me of its memories\nYou sang it to me, devoted to me in whole\nI almost think, when I hear your voice\nThis is only a dream\n\nWhen you left your song was still playing in my heart\nPerhaps the same song brought new happiness to another\nI'm still playing your record, even though it's worn\nMy memory just can't wear out\n\nI'm still playing your record, even though it's worn\nMy memory juѕt can't wear out\n\nLa la la la la, la la la la la…\nLa la la la la la la la…\nLa la la la la, la la la la la…\nLa la la la la la la lа…"
        }
    ],
    "videoUrls": [
        "https://www.youtube-nocookie.com/embed/mIo8JxprBN0",
        "https://www.youtube.com/embed/qX0oNRq1Rys"
    ],
    "dancers": null,
    "backings": null,
    "composers": null,
    "lyricists": null,
    "writers": [
        "Börje Sundgren"
    ],
    "conductor": "George de Godzinsky",
    "stageDirector": null,
    "tone": "D major",
    "bpm": 111,
    "broadcaster": "YLE",
    "spokesperson": "Poppe Berg",
    "commentators": [
        "Aarno Walli"
    ]
}