{
    "id": 25,
    "country": "HR",
    "artist": "Mia Dimšić",
    "song": "Guilty Pleasure",
    "lyrics": [
        {
            "languages": [
                "English"
            ],
            "title": "Guilty Pleasure",
            "content": "Dreamt of you last night\nWoke up, you weren't there\nFive nights in a row\nOf dreams I've never shared\n\nYou come without a warning\nEarly in the morning\nTiming's never been our thing\nLeaving me with guilt\nThe only souvenir you bring\n\nI'm with him and you're a secret treasure\nHe's devotion, you're a guilty pleasure\nI'm with him and this is real life, honey\nGuess the joke's no longer funny\n\nI'm with him until the death do us part\nBut it doesn't do for this hungry heart\nI'm with him, but in my frantic head\nYou always come and say\n\nWould you run away?\nWould you run away with me?\nWould you run away?\nWould you run away?\n\nOne love is enough\nThat's all you ever get\nLeast that's what they tell you\nStill, I can't forget\n\nEyes like burning ashes\n'Til the sunlight flashes\nCan't recall what I've been taught\nCaptivated by the thunderstorm\nIn which I'm caught\n\nI'm with him and you're a secret treasure\nHe's devotion, you're a guilty pleasure\nI'm with him and this is real life, honey\nGuess the joke's no longer funny\n\nI'm with him until the death do us part\nBut it doesn't do for this hungry heart\nI'm with him, but in my frantic head\nYou always come and say\n\nWould you run away?\nWould you run away with me?\nWould you run away?\nWould you run away?\n\nIn this real life, there's no way\nIn this real life, I have to stay\nIn this real life, there's no way\nIn this real life\n\nI'm with him and you're a secret treasure\nHe's devotion, you're a guilty pleasure\nI'm with him and this is real life, honey\nGuess the joke's no longer funny\n\nI'm with him until the death do us part\nBut it doesn't do for this hungry heart\nI'm with him, but in my frantic head\nYou always come and say, say, say\n\nWould you run away?\nWould you run away with me?\nWould you run away?\nWould you run away?\n\nIn this real life, there's no way\nIn this real life, I have to stay\nIn this real life, there's no way\nIn thiѕ reаl life"
        },
        {
            "languages": [
                "Croatian"
            ],
            "title": "Tajni užitak",
            "content": "Sanjala sam te prošlu noć\nProbudila sam se, nisi bio ondje\nPet noći zaredom\nSnova koje nikad nisam podijelila\n\nDošao si bez upozorenja\nRano ujutro\nTajming nikad nije bila naša stvar\nOstavljaš me s krivnjom\nJedinim suvenirom koji donosiš\n\nJa sam s njim, a ti si skriveno blago\nOn je predanost, ti si tajni užitak\nJa sam s njim i ovo je pravi život, dušo\nIzgleda da šala više nije smiješna\n\nJa sam s njim dok nas smrt ne rastavi\nAli to nije utjeha ovom gladnom srcu\nJa sam s njim, ali u mojoj mahnitoj glavi\nUvijek dolaziš ti i kažeš\n\nBi li pobjegla?\nBi li pobjegla sa mnom?\nBi li pobjegla?\nBi li pobjegla?\n\nJedna je ljubav dovoljna\nTo je sve što ćeš ikada dobiti\nBarem je to ono što ti kažu\nIpak, ja ne mogu zaboraviti\n\nOči poput plamtećeg ognja\nDo izlaska sunca\nNe mogu se sjetiti što su me naučili\nOčarana olujom\nU koju sam uhvaćena\n\nJa sam s njim, a ti si skriveno blago\nOn je predanost, ti si tajni užitak\nJa sam s njim i ovo je pravi život, dušo\nIzgleda da šala više nije smiješna\n\nJa sam s njim dok nas smrt ne rastavi\nAli to nije utjeha ovom gladnom srcu\nJa sam s njim, ali u mojoj mahnitoj glavi\nUvijek dolaziš ti i kažeš\n\nBi li pobjegla?\nBi li pobjegla sa mnom?\nBi li pobjegla?\nBi li pobjegla?\n\nU ovom pravom životu nema šanse\nU ovom pravom životu moram ostati\nU ovom pravom životu nema šanse\nU ovom pravom život\n\nJa sam s njim, a ti si skriveno blago\nOn je predanost, ti si tajni užitak\nJa sam s njim i ovo je pravi život, dušo\nIzgleda da šala više nije smiješna\n\nJa sam s njim dok nas smrt ne rastavi\nAli to nije utjeha ovom gladnom srcu\nJa sam s njim, ali u mojoj mahnitoj glavi\nUvijek dolaziš ti i kažeš\n\nBi li pobjegla?\nBi li pobjegla sa mnom?\nBi li pobjegla?\nBi li pobjegla?\n\nU ovom pravom životu nema šanse\nU ovom pravom životu moram ostati\nU ovom pravom životu nema šanѕe\nU ovom prаvom život"
        },
        {
            "languages": [
                "Finnish"
            ],
            "title": "Syyllinen Nautinto",
            "content": "Uneksin sinusta viime yönä\nHeräsin, et ollut siellä\nViisi yötä peräkkäin\nUnelmista, joita en ole koskaan jakanut\n\nSaavut ilman varoitusta\nAikaisin aamulla\nAjoitus ei koskaan ole ollut meidän juttumme\nJättäen minut syyllisyyteen\nAinoa muisto, jonka tuot mukanasi\n\nSeksi hänen kanssaan, sinä olet salainen aarre\nHän on omistautumista, sinä olet syyllinen nautinto\nOlen hänen kanssaan, ja tämä on todellinen elämä, kulta\nArvaa, että vitsi ei enää ole hauska\n\nOlen hänen kanssaan, kunnes kuolema meidät erottaa\nMutta se ei riitä tälle nälkäiselle sydämelle\nOlen hänen kanssaan, mutta levottomassa päässäni\nSinä tulet aina ja sanot\n\nJuoksisitko karkuun?\nJuoksisitko karkuun kanssani?\nJuoksisitko karkuun?\nJuoksisitko karkuun?\n\nYksi rakkaus riittää\nSe on kaikki mitä koskaan saat\nVähintään niin he sinulle kertovat\nSilti, en voi unohtaa\n\nSilmät kuin palavat tuhkat\nKunnes auringonsäteet välähtävät\nEn muista mitä minulle on opetettu\nLumoutunut ukonilmasta\nJohon olen joutunut\n\nSeksi hänen kanssaan, sinä olet salainen aarre\nHän on omistautumista, sinä olet syyllinen nautinto\nOlen hänen kanssaan, ja tämä on todellinen elämä, kulta\nArvaa, että vitsi ei enää ole hauska\n\nOlen hänen kanssaan, kunnes kuolema meidät erottaa\nMutta se ei riitä tälle nälkäiselle sydämelle\nOlen hänen kanssaan, mutta levottomassa päässäni\nSinä tulet aina ja sanot\n\nJuoksisitko karkuun?\nJuoksisitko karkuun kanssani?\nJuoksisitko karkuun?\nJuoksisitko karkuun?\n\nTässä todellisessa elämässä, ei ole mitään tapaa\nTässä todellisessa elämässä, minun täytyy jäädä\nTässä todellisessa elämässä, ei ole mitään tapaa\nTässä todellisessa elämässä\n\nSeksi hänen kanssaan, sinä olet salainen aarre\nHän on omistautumista, sinä olet syyllinen nautinto\nOlen hänen kanssaan, ja tämä on todellinen elämä, kulta\nArvaa, että vitsi ei enää ole hauska\n\nOlen hänen kanssaan, kunnes kuolema meidät erottaa\nMutta se ei riitä tälle nälkäiselle sydämelle\nOlen hänen kanssaan, mutta levottomassa päässäni\nTulet aina ja sanot, sanot, sanot\n\nJuoksisitko karkuun?\nJuoksisitko karkuun kanssani?\nJuoksisitko karkuun?\nJuoksisitko karkuun?\n\nTässä todellisessa elämässä, ei ole mitään tapaa\nTässä todellisessa elämässä, minun täytyy jäädä\nTässä todellisessa elämässä, ei ole mitään tapaa\nTässä todellisessа elämäsѕä"
        }
    ],
    "videoUrls": [
        "https://www.youtube-nocookie.com/embed/9vBQdtW3mJE",
        "https://www.youtube.com/embed/VdOitl6KekY",
        "https://www.youtube.com/embed/iiOyTKQZF8k",
        "https://www.youtube.com/embed/DFBwe2w0zO4",
        "https://www.youtube.com/embed/SX_hfZPPPyk",
        "https://www.youtube.com/embed/WT4TfJfsfmg",
        "https://www.youtube.com/embed/JazV54JLxOE",
        "https://www.youtube.com/embed/pimrCbKP_IM"
    ],
    "dancers": [
        "Josip Palameta",
        "Rebecca Krajnović",
        "Roman Vrančić"
    ],
    "backings": [
        "Bruna Oberan",
        "Danon Vrlić"
    ],
    "composers": null,
    "lyricists": null,
    "writers": [
        "Damir Bačić",
        "Mia Dimšić",
        "Vjekoslav Dimter"
    ],
    "conductor": null,
    "stageDirector": "Nejc Levstik",
    "tone": "F major",
    "bpm": 84,
    "broadcaster": "HRT",
    "spokesperson": "Ivan Dorian Molnar",
    "commentators": [
        "Duško Ćurlić"
    ]
}