{
    "id": 34,
    "country": "SI",
    "artist": "Quartissimo feat. Martina",
    "song": "Love Symphony",
    "lyrics": [
        {
            "languages": [
                "Slovene & English"
            ],
            "title": "Love Symphony",
            "content": "Rodi se in umre\nKot krog obrača se\nLe jaz in ti sva vse\nTo simfonija je\n\nRodi se in umre\nKot krog obrača se\nLe jaz in ti sva vse\nTo simfonija je\n\nOut of time, out of place\nSomewhere inside my universe\nWhere you live your dreams\n\nImagine you and me\nWe're flying above the sea\nFeeling free eternаlly\nLike in this love ѕymphony"
        },
        {
            "languages": [
                "English"
            ],
            "title": "Love symphony",
            "content": "It's born and it dies\nTurning like a circle\nOnly you and I are everything\nThat's a symphony\n\nIt's born and it dies\nTurning like a circle\nOnly you and I are everything\nThat's a symphony\n\nOut of time, out of place\nSomewhere inside my universe\nWhere you live your dreams\n\nImagine you and me\nWe're flying above the sea\nFeeling free eternаlly\nLike in this love ѕymphony"
        }
    ],
    "videoUrls": [
        "https://www.youtube-nocookie.com/embed/zql3IGp4zO4",
        "https://www.youtube.com/embed/afPh1slPAsc",
        "https://www.youtube.com/embed/UgDppbQpb-c"
    ],
    "dancers": null,
    "backings": null,
    "composers": [
        "Aleksandar Valenčić",
        "Andrej Babić"
    ],
    "lyricists": [
        "Andrej Babić"
    ],
    "writers": null,
    "conductor": null,
    "stageDirector": "Miha Alujevič",
    "tone": "A minor",
    "bpm": 132,
    "broadcaster": "RTVSLO",
    "spokesperson": "Peter Poles",
    "commentators": [
        "Andrej Hofer"
    ]
}